<TranslationLeaf>
	<value>
		Ø
	</value>
	<dit>
		<value>
			E
		</value>
		<dit>
			<value>
				I
			</value>
			<dit>
				<value>
					S
				</value>
				<dit>
					<value>
						H
					</value>
					<dit>
						<value>
							5
						</value>
					</dit>
					<dah>
						<value>
							4
						</value>
					</dah>
				</dit>
				<dah>
					<value>
						V
					</value>
					<dit>
						<value>
							3
						</value>
					</dit>
					<dah>
						<value>
							Ŝ
						</value>
						<dah>
							<value>
								✅
							</value>
						</dah>
					</dah>
				</dah>
			</dit>
			<dah>
				<value>
					U
				</value>
				<dit>
					<value>
						F
					</value>
					<dit>
						<value>
							É
						</value>
					</dit>
					<dah>
						<value>
							¿
						</value>
					</dah>
				</dit>
				<dah>
					<value>
						Ü
					</value>
					<dit>
						<value>
							Đ
						</value>
						<dit>
							<value>
								?
							</value>
						</dit>
						<dah>
							<value>
								_
							</value>
						</dah>
					</dit>
					<dah>
						<value>
							2
						</value>
					</dah>
				</dah>
			</dah>
		</dit>
		<dah>
			<value>
				A
			</value>
			<dit>
				<value>
					R
				</value>
				<dit>
					<value>
						L
					</value>
					<dit>
						<value>
							&amp;
						</value>
					</dit>
					<dah>
						<value>
							È
						</value>
						<dit>
							<value>
								"
							</value>
						</dit>
					</dah>
				</dit>
				<dah>
					<value>
						Æ
					</value>
					<dit>
						<value>
							+
						</value>
						<dah>
							<value>
								.
							</value>
						</dah>
					</dit>
				</dah>
			</dit>
			<dah>
				<value>
					W
				</value>
				<dit>
					<value>
						P
					</value>
					<dit>
						<value>
							þ
						</value>
					</dit>
					<dah>
						<value>
							À
						</value>
						<dit>
							<value>
								@
							</value>
						</dit>
					</dah>
				</dit>
				<dah>
					<value>
						J
					</value>
					<dit>
						<value>
							Ĵ
						</value>
					</dit>
					<dah>
						<value>
							1
						</value>
						<dit>
							<value>
								'
							</value>
						</dit>
					</dah>
				</dah>
			</dah>
		</dah>
	</dit>
	<dah>
		<value>
			T
		</value>
		<dit>
			<value>
				N
			</value>
			<dit>
				<value>
					D
				</value>
				<dit>
					<value>
						B
					</value>
					<dit>
						<value>
							6
						</value>
						<dah>
							<value>
								0
							</value>
						</dah>
					</dit>
					<dah>
						<value>
							=
						</value>
					</dah>
				</dit>
				<dah>
					<value>
						X
					</value>
					<dit>
						<value>
							/
						</value>
					</dit>
				</dah>
			</dit>
			<dah>
				<value>
					K
				</value>
				<dit>
					<value>
						C
					</value>
					<dit>
						<value>
							Ĉ
						</value>
					</dit>
					<dah>
						<value>
              👋
						</value>
						<dit>
							<value>
								;
							</value>
						</dit>
						<dah>
							<value>
								!
							</value>
						</dah>
					</dah>
				</dit>
				<dah>
					<value>
						Y
					</value>
					<dit>
						<value>
							(
						</value>
						<dah>
							<value>
								)
							</value>
						</dah>
					</dit>
				</dah>
			</dah>
		</dit>
		<dah>
			<value>
				M
			</value>
			<dit>
				<value>
					G
				</value>
				<dit>
					<value>
						Z
					</value>
					<dit>
						<value>
							7
						</value>
					</dit>
					<dah>
						<value>
							Ż
						</value>
						<dit>
							<value>
								Ź
							</value>
						</dit>
						<dah>
							<value>
								,
							</value>
						</dah>
					</dah>
				</dit>
				<dah>
					<value>
						Q
					</value>
					<dit>
						<value>
							Ĝ
						</value>
					</dit>
					<dah>
						<value>
							Ñ
						</value>
					</dah>
				</dah>
			</dit>
			<dah>
				<value>
					O
				</value>
				<dit>
					<value>
						Ó
					</value>
					<dit>
						<value>
							8
						</value>
						<dit>
							<value>
								:
							</value>
						</dit>
					</dit>
				</dit>
				<dah>
					<value>
						Ĥ
					</value>
					<dit>
						<value>
							9
						</value>
					</dit>
					<dah>
						<value>
							0
						</value>
					</dah>
				</dah>
			</dah>
		</dah>
	</dah>
</TranslationLeaf>
